mini_version_manager/__init__.py
mini_version_manager/mini_version_manager.py
mini_version_manager-0.0.8.dist-info/LICENSE
mini_version_manager-0.0.8.dist-info/METADATA
mini_version_manager-0.0.8.dist-info/WHEEL
mini_version_manager-0.0.8.dist-info/top_level.txt
mini_version_manager-0.0.8.dist-info/RECORD
