Metadata-Version: 2.2
Name: mini_version_manager
Version: 0.0.8
Summary: A simple version management tool
Home-page: https://www.deepseek.com/
Author: bjk
Author-email: bjk <228558063@qq.com>
Project-URL: Homepage, https://www.deepseek.com/
Classifier: Programming Language :: Python :: 3
Classifier: License :: OSI Approved :: MIT License
Classifier: Operating System :: OS Independent
Requires-Python: >=3.9
License-File: LICENSE
Dynamic: author
Dynamic: home-page
Dynamic: requires-python
